LICENSE
MANIFEST.in
README.rst
setup.cfg
setup.py
tangled.mako.egg-info/PKG-INFO
tangled.mako.egg-info/SOURCES.txt
tangled.mako.egg-info/dependency_links.txt
tangled.mako.egg-info/requires.txt
tangled.mako.egg-info/top_level.txt
tangled/mako/__init__.py
tangled/mako/tests/__init__.py
tangled/mako/tests/test_lookup.py
tangled/mako/tests/templates/test.mako