Metadata-Version: 1.1
Name: tangled.mako
Version: 1.0a5
Summary: Tangled Mako integration
Home-page: http://tangledframework.org/
Author: Wyatt Baldwin
Author-email: self@wyattbaldwin.com
License: UNKNOWN
Download-URL: https://github.com/TangledWeb/tangled.mako/tags
Platform: UNKNOWN
Classifier: Development Status :: 3 - Alpha
Classifier: Intended Audience :: Developers
Classifier: License :: OSI Approved :: MIT License
Classifier: Programming Language :: Python :: 3
Classifier: Programming Language :: Python :: 3.3
Classifier: Programming Language :: Python :: 3.4
Classifier: Programming Language :: Python :: 3.5
